eccw/__init__.py
eccw/eccw_compute.py
eccw/eccw_explore.py
eccw/eccw_plot.py
eccw-1.1.2.dist-info/LICENCE.txt
eccw-1.1.2.dist-info/METADATA
eccw-1.1.2.dist-info/WHEEL
eccw-1.1.2.dist-info/top_level.txt
eccw-1.1.2.dist-info/RECORD
