Metadata-Version: 2.1
Name: eccw
Version: 1.1.2
Summary: Exact Critical Coulomb Wedge : tools to compute and display the exact solution of any parameter of Critical Coulomb Wedge
Home-page: https://github.com/bclmary/eccw
Author: BCL Mary, YM Leroy, Xiaoping Yuan
Author-email: baptiste.mary@cyu.fr
Maintainer: BCL Mary
Maintainer-email: bclmary@mailoo.org
License: GPL-3.0+
Keywords: geology,accretionnary prism
Platform: any
Classifier: Development Status :: 5 - Production/Stable
Classifier: License :: OSI Approved :: GNU General Public License v3 or later (GPLv3+)
Classifier: Natural Language :: English
Classifier: Environment :: Console
Classifier: Programming Language :: Python :: 3 :: Only
Classifier: Intended Audience :: Science/Research
Classifier: Operating System :: POSIX
Classifier: Operating System :: POSIX :: Linux
Classifier: Operating System :: Microsoft :: Windows
Classifier: Operating System :: Microsoft :: Windows :: Windows 7
Classifier: Operating System :: Microsoft :: Windows :: Windows 10
Classifier: Topic :: Scientific/Engineering
Classifier: Topic :: Education
Requires-Python: >=3.6
License-File: LICENCE.txt
Requires-Dist: matplotlib (>=3.1)
Requires-Dist: numpy (>=1.10)
